eservice_unlock_pdf/__init__.py
eservice_unlock_pdf/unlock.py
eservice_unlock_pdf-0.1.2.dist-info/METADATA
eservice_unlock_pdf-0.1.2.dist-info/WHEEL
eservice_unlock_pdf-0.1.2.dist-info/top_level.txt
eservice_unlock_pdf-0.1.2.dist-info/RECORD
