Metadata-Version: 2.2
Name: eservice-unlock-pdf
Version: 0.1.2
Summary: A Python package to unlock password-protected PDF files
Home-page: https://github.com/abcprintf/python-unlock-pdf
Author: abcprintf
Author-email: abcprintf@gmail.com
Project-URL: Documentation, https://github.com/abcprintf/python-unlock-pdf
Project-URL: Source, https://github.com/abcprintf/python-unlock-pdf
Project-URL: Tracker, https://github.com/abcprintf/python-unlock-pdf/issues
Classifier: Programming Language :: Python :: 3
Classifier: License :: OSI Approved :: MIT License
Classifier: Operating System :: OS Independent
Requires-Python: >=3.11
Requires-Dist: pikepdf
Dynamic: author
Dynamic: author-email
Dynamic: classifier
Dynamic: description
Dynamic: description-content-type
Dynamic: home-page
Dynamic: project-url
Dynamic: requires-dist
Dynamic: requires-python
Dynamic: summary
